{
	"configurations" : 
	[
		{
			"directories" : 
			[
				{
					"build" : ".",
					"minimumCMakeVersion" : 
					{
						"string" : "3.5.0"
					},
					"projectIndex" : 0,
					"source" : ".",
					"targetIndexes" : 
					[
						0
					]
				}
			],
			"name" : "Debug",
			"projects" : 
			[
				{
					"directoryIndexes" : 
					[
						0
					],
					"name" : "exp01",
					"targetIndexes" : 
					[
						0
					]
				}
			],
			"targets" : 
			[
				{
					"directoryIndex" : 0,
					"id" : "exp01::@6890427a1f51a3e7e1df",
					"jsonFile" : "target-exp01-Debug-4059774289e413bddaf1.json",
					"name" : "exp01",
					"projectIndex" : 0
				}
			]
		}
	],
	"kind" : "codemodel",
	"paths" : 
	{
		"build" : "C:/Users/53065/Documents/Code/digital-image-processing/exp01/build",
		"source" : "C:/Users/53065/Documents/Code/digital-image-processing/exp01"
	},
	"version" : 
	{
		"major" : 2,
		"minor" : 0
	}
}
